{
  "extends": "solhint:recommended",
  "plugins": ["prettier"],
  "rules": {
    "compiler-version": ["error", "^0.8.20"],
    "func-visibility": ["warn", { "ignoreConstructors": true }],
    "not-rely-on-time": "off",
    "avoid-low-level-calls": "warn",
    "avoid-call-value": "warn",
    "avoid-tx-origin": "error",
    "check-send-result": "error",
    "func-name-mixedcase": "warn",
    "var-name-mixedcase": "warn",
    "const-name-snakecase": "warn",
    "modifier-name-mixedcase": "warn",
    "contract-name-camelcase": "warn",
    "event-name-camelcase": "warn",
    "max-line-length": ["warn", 120],
    "no-empty-blocks": "warn",
    "no-unused-vars": "warn",
    "no-console": "warn",
    "reason-string": ["warn", { "maxLength": 64 }],
    "constructor-syntax": "error",
    "quotes": ["error", "double"],
    "gas-custom-errors": "warn",
    "private-vars-leading-underscore": "warn",
    "immutable-vars-naming": "warn"
  }
}
